odoo9_addon_quality_control-9.0.1.3.0.99.dev23-py3.8-nspkg.pth
odoo_addons/quality_control/README.rst
odoo_addons/quality_control/__init__.py
odoo_addons/quality_control/__openerp__.py
odoo_addons/quality_control/data/quality_control_data.xml
odoo_addons/quality_control/demo/quality_control_demo.xml
odoo_addons/quality_control/i18n/am.po
odoo_addons/quality_control/i18n/ar.po
odoo_addons/quality_control/i18n/bg.po
odoo_addons/quality_control/i18n/bs.po
odoo_addons/quality_control/i18n/ca.po
odoo_addons/quality_control/i18n/ca_ES.po
odoo_addons/quality_control/i18n/cs.po
odoo_addons/quality_control/i18n/da.po
odoo_addons/quality_control/i18n/da_DK.po
odoo_addons/quality_control/i18n/de.po
odoo_addons/quality_control/i18n/el_GR.po
odoo_addons/quality_control/i18n/en_AU.po
odoo_addons/quality_control/i18n/en_GB.po
odoo_addons/quality_control/i18n/es.po
odoo_addons/quality_control/i18n/es_AR.po
odoo_addons/quality_control/i18n/es_CL.po
odoo_addons/quality_control/i18n/es_CO.po
odoo_addons/quality_control/i18n/es_CR.po
odoo_addons/quality_control/i18n/es_DO.po
odoo_addons/quality_control/i18n/es_EC.po
odoo_addons/quality_control/i18n/es_ES.po
odoo_addons/quality_control/i18n/es_MX.po
odoo_addons/quality_control/i18n/es_PE.po
odoo_addons/quality_control/i18n/es_PY.po
odoo_addons/quality_control/i18n/es_VE.po
odoo_addons/quality_control/i18n/et.po
odoo_addons/quality_control/i18n/eu.po
odoo_addons/quality_control/i18n/fa.po
odoo_addons/quality_control/i18n/fi.po
odoo_addons/quality_control/i18n/fr.po
odoo_addons/quality_control/i18n/fr_CA.po
odoo_addons/quality_control/i18n/fr_CH.po
odoo_addons/quality_control/i18n/fr_FR.po
odoo_addons/quality_control/i18n/gl.po
odoo_addons/quality_control/i18n/gl_ES.po
odoo_addons/quality_control/i18n/he.po
odoo_addons/quality_control/i18n/hi.po
odoo_addons/quality_control/i18n/hr.po
odoo_addons/quality_control/i18n/hr_HR.po
odoo_addons/quality_control/i18n/hu.po
odoo_addons/quality_control/i18n/id.po
odoo9_addon_quality_control-9.0.1.3.0.99.dev23.dist-info/METADATA
odoo9_addon_quality_control-9.0.1.3.0.99.dev23.dist-info/WHEEL
odoo9_addon_quality_control-9.0.1.3.0.99.dev23.dist-info/namespace_packages.txt
odoo9_addon_quality_control-9.0.1.3.0.99.dev23.dist-info/top_level.txt
odoo9_addon_quality_control-9.0.1.3.0.99.dev23.dist-info/RECORD
