Metadata-Version: 2.1
Name: odoo9-addon-quality-control
Version: 9.0.1.3.0.99.dev23
Summary: Quality control
Home-page: http://www.odoomrp.com
Author: OdooMRP team, AvanzOSC, Serv. Tecnol. Avanzados - Pedro M. Baeza, Eficent, Odoo Community Association (OCA)
Author-email: support@odoo-community.org
License: AGPL-3
Platform: UNKNOWN
Classifier: Programming Language :: Python
Classifier: Framework :: Odoo
Classifier: Framework :: Odoo :: 9.0
Classifier: License :: OSI Approved :: GNU Affero General Public License v3
Requires-Python: ~=2.7
Requires-Dist: odoo (<9.1a,>=9.0a)
